{
    "APIKeys": {
        "Steam": ""
    },
    "ActiveExtensions": {
        "adverts": false,
        "afkkick": false,
        "autoperfprofile": false,
        "badges": true,
        "ban": true,
        "basecommands": true,
        "botmanager": false,
        "commbans": false,
        "customspawns": false,
        "customtextcommands": false,
        "disablevanillavotes": false,
        "enforceteamsizes": false,
        "epsilonbadges": true,
        "extraips": false,
        "funcommands": true,
        "hiveteamrestriction": false,
        "improvedchat": true,
        "killstreak": false,
        "logging": true,
        "mapstats": false,
        "mapvote": false,
        "motd": true,
        "namefilter": false,
        "norookies": false,
        "ns2panel": true,
        "nsl": true,
        "nsltournamentbadges": true,
        "passwordreset": true,
        "pingtracker": false,
        "pregame": false,
        "pregameplus": false,
        "readyroom": false,
        "readyroomqueue": false,
        "reservedslots": false,
        "roundlimiter": false,
        "serverswitch": false,
        "tournamentmode": false,
        "unstuck": false,
        "usermanagement": true,
        "vacplus": false,
        "verboselogging": false,
        "votealltalk": false,
        "votedraw": false,
        "voterandom": false,
        "votesurrender": true,
        "welcomemessages": true,
        "wonitor": true,
        "workshopupdater": false
    },
    "AddTag": true,
    "ChatName": "Admin",
    "ConsoleName": "Admin",
    "DateFormat": "dd-mm-yyyy",
    "DebugLogging": false,
    "EnableLogging": true,
    "EqualsCanTarget": false,
    "ExtensionDir": "config://shine/plugins/",
    "GetUsersFromWeb": false,
    "GetUsersWithPOST": false,
    "LogDir": "config://shine/logs/",
    "LogLevel": "INFO",
    "MaxCommandsPerSecond": 3,
    "NotifyAdminAnonymous": false,
    "NotifyAnonymous": true,
    "NotifyOnCommand": false,
    "RefreshInterval": 60,
    "RefreshUsers": false,
    "ReportErrors": true,
    "SilentChatCommands": true,
    "UserRetrieveArguments": [],
    "UsersURL": "http://www.yoursite.com/users.json",
    "WebConfigs": {
        "Enabled": false,
        "IsBlacklist": false,
        "MaxAttempts": 3,
        "Plugins": [],
        "RequestArguments": [],
        "RequestURL": "",
        "UpdateInterval": 1,
        "UpdateMode": 1
    },
    "__Version": "1.0"
}